Metadata-Version: 2.1
Name: pypinn
Version: 1.0.0
Summary: pinn implementation using torch.
Home-page: UNKNOWN
Author: Dongpeng Han
Author-email: 3223003076@qq.com
License: UNKNOWN
Keywords: python,pinn,pypinn,windows,mac,linux
Platform: UNKNOWN
Classifier: Development Status :: 1 - Planning
Classifier: Intended Audience :: Developers
Classifier: Programming Language :: Python :: 3
Classifier: Operating System :: Unix
Classifier: Operating System :: MacOS :: MacOS X
Classifier: Operating System :: Microsoft :: Windows
